pyuvsim/__init__.py
pyuvsim/antenna.py
pyuvsim/baseline.py
pyuvsim/cli.py
pyuvsim/mpi.py
pyuvsim/profiling.py
pyuvsim/simsetup.py
pyuvsim/telescope.py
pyuvsim/utils.py
pyuvsim/uvsim.py
pyuvsim/data/28mEWbl_10time_10chan.uvfits
pyuvsim/data/28mEWbl_1time_1chan.uvfits
pyuvsim/data/28m_triangle_10time_10chan.uvfits
pyuvsim/data/5km_triangle_1time_1chan.uvfits
pyuvsim/data/5km_triangle_layout.csv
pyuvsim/data/HERA_NicCST.beamfits
pyuvsim/data/HERA_layout.csv
pyuvsim/data/__init__.py
pyuvsim/data/baseline_lite.csv
pyuvsim/data/baseline_lite_4x.csv
pyuvsim/data/baseline_lite_multi_beam.csv
pyuvsim/data/bl_lite_mixed.yaml
pyuvsim/data/bl_lite_mixed_constructors.yaml
pyuvsim/data/gleam_50srcs.vot
pyuvsim/data/gleam_triangle_2freq_flat.uvh5
pyuvsim/data/gleam_triangle_2freq_spectral_index.uvh5
pyuvsim/data/gleam_triangle_2freq_subband.uvh5
pyuvsim/data/gleam_triangle_flat.uvh5
pyuvsim/data/gleam_triangle_spectral_index.uvh5
pyuvsim/data/gleam_triangle_subband.uvh5
pyuvsim/data/mock_catalog_heratext_2458098.27471265.txt
pyuvsim/data/moon_config_uniform.yaml
pyuvsim/data/mwa128_config.yaml
pyuvsim/data/mwa128_layout_longbl.csv
pyuvsim/data/mwa88_nocore_config.yaml
pyuvsim/data/mwa88_nocore_config_dipole.yaml
pyuvsim/data/mwa_128T_layout.csv
pyuvsim/data/mwa_config_airy.yaml
pyuvsim/data/mwa_config_gauss.yaml
pyuvsim/data/mwa_config_multi_beam.yaml
pyuvsim/data/mwa_config_short_dipole.yaml
pyuvsim/data/mwa_config_uniform.yaml
pyuvsim/data/mwa_config_uvbeam.yaml
pyuvsim/data/mwa_nocore_layout.csv
pyuvsim/data/profiling_params.yaml
pyuvsim/data/single_source.txt
pyuvsim/data/single_source.vot
pyuvsim/data/test_layout_6ant.csv
pyuvsim/data/testfile_singlesource.uvh5
pyuvsim/data/tranquility_config.yaml
pyuvsim/data/test_catalogs/MOON.txt
pyuvsim/data/test_catalogs/R.txt
pyuvsim/data/test_catalogs/RASG.txt
pyuvsim/data/test_catalogs/mock_cross_2458098.27471.txt
pyuvsim/data/test_catalogs/mock_hera_text_2458098.27471.txt
pyuvsim/data/test_catalogs/mock_long-line_2458098.27471.txt
pyuvsim-1.4.2.dist-info/licenses/LICENSE
pyuvsim-1.4.2.dist-info/METADATA
pyuvsim-1.4.2.dist-info/WHEEL
pyuvsim-1.4.2.dist-info/entry_points.txt
pyuvsim-1.4.2.dist-info/top_level.txt
pyuvsim-1.4.2.dist-info/RECORD
