Metadata-Version: 2.4
Name: pyuvsim
Version: 1.4.2
Summary: Python objects and interfaces for representing diffuse, extended and compact astrophysical radio sources
Author-email: Adam Lanman <alanman@mit.edu>, Bryna Hazelton <brynah@phys.washington.edu>, Daniel Jacobs <wheresmytab@gmail.com>, Matthew Kolopanis <mjkolopa@asu.edu>, Jonathan Pober <jonathan_pober@brown.edu>, James Aguirre <jaguirre@sas.upenn.edu>, Nithyanandan Thyagarajan <nithyanandan.t@gmail.com>, Steven Murray <murray.steveng@gmail.com>
Maintainer-email: Bryna Hazelton <brynah@phys.washington.edu>, Matthew Kolopanis <mjkolopa@asu.edu>
Project-URL: Repository, https://github.com/RadioAstronomySoftwareGroup/pyuvsim
Project-URL: Documentation, https://pyuvsim.readthedocs.io/
Keywords: radio astronomy,interferometry
Classifier: License :: OSI Approved :: BSD License
Classifier: Development Status :: 5 - Production/Stable
Classifier: Intended Audience :: Science/Research
Classifier: License :: OSI Approved :: BSD License
Classifier: Programming Language :: Python :: 3.11
Classifier: Programming Language :: Python :: 3.12
Classifier: Programming Language :: Python :: 3.13
Classifier: Topic :: Scientific/Engineering :: Astronomy
Classifier: Operating System :: Microsoft :: Windows
Classifier: Operating System :: POSIX
Classifier: Operating System :: MacOS
Requires-Python: >=3.11
License-File: LICENSE
Requires-Dist: astropy>=6.0
Requires-Dist: numpy>=1.23
Requires-Dist: psutil
Requires-Dist: pyradiosky>=1.1.0
Requires-Dist: pyuvdata>=3.2.3
Requires-Dist: pyyaml>=5.4.1
Requires-Dist: scipy>=1.9
Requires-Dist: setuptools>=64
Requires-Dist: setuptools_scm>=8.1
Provides-Extra: casa
Requires-Dist: python-casacore>=3.5.2; extra == "casa"
Provides-Extra: healpix
Requires-Dist: astropy-healpix>=1.0.2; extra == "healpix"
Provides-Extra: moon
Requires-Dist: lunarsky>=0.2.5; extra == "moon"
Provides-Extra: plot
Requires-Dist: matplotlib>=3.6; extra == "plot"
Provides-Extra: sim
Requires-Dist: mpi4py>=3.1.3; extra == "sim"
Requires-Dist: psutil; extra == "sim"
Provides-Extra: sim-test
Requires-Dist: pyuvsim[sim,test]; extra == "sim-test"
Requires-Dist: mpi-pytest>=2025.7.0; extra == "sim-test"
Provides-Extra: all
Requires-Dist: pyuvsim[casa,healpix,moon,plot,sim]; extra == "all"
Provides-Extra: test
Requires-Dist: coverage; extra == "test"
Requires-Dist: pooch>=1.8; extra == "test"
Requires-Dist: pre-commit; extra == "test"
Requires-Dist: pytest; extra == "test"
Requires-Dist: pytest-cov>=5.0; extra == "test"
Provides-Extra: doc
Requires-Dist: matplotlib; extra == "doc"
Requires-Dist: pypandoc; extra == "doc"
Requires-Dist: sphinx; extra == "doc"
Provides-Extra: profiler
Requires-Dist: line-profiler; extra == "profiler"
Provides-Extra: dev
Requires-Dist: pyuvsim[all,doc,profiler,sim-test,test]; extra == "dev"
Provides-Extra: windows-dev
Requires-Dist: pyuvsim[doc,healpix,profiler,sim,sim-test,test]; extra == "windows-dev"
Dynamic: license-file
